htmtl/__init__.py
htmtl/expression_parser.py
htmtl/htmtl.py
htmtl/modifier.py
htmtl/parser.py
htmtl/modifiers/__init__.py
htmtl/modifiers/truncate.py
htmtl/parsers/__init__.py
htmtl/parsers/generic_value.py
htmtl/parsers/inner_html.py
htmtl/parsers/inner_partial.py
htmtl/parsers/inner_text.py
htmtl/parsers/iterate.py
htmtl/parsers/outer_html.py
htmtl/parsers/outer_partial.py
htmtl/parsers/outer_text.py
htmtl/parsers/when.py
htmtl/parsers/when_not.py
htmtl-0.2.0.dist-info/METADATA
htmtl-0.2.0.dist-info/WHEEL
htmtl-0.2.0.dist-info/top_level.txt
htmtl-0.2.0.dist-info/RECORD
