Metadata-Version: 2.2
Name: htmtl
Version: 0.2.0
Summary: A templating language that is both a superset and subset of HTML.
Author-email: Asko Nõmm <asko@nmm.ee>
Classifier: Programming Language :: Python :: 3
Classifier: License :: OSI Approved :: MIT License
Classifier: Operating System :: OS Independent
Classifier: Development Status :: 1 - Planning
Requires-Python: >=3.10
Requires-Dist: dompa>=0.9.0
